setup.py
tardy/__init__.py
tardy/cmd.py
tardy/lib.py
tardy.egg-info/PKG-INFO
tardy.egg-info/SOURCES.txt
tardy.egg-info/dependency_links.txt
tardy.egg-info/entry_points.txt
tardy.egg-info/top_level.txt