Metadata-Version: 1.0
Name: tardy
Version: 0.1.7
Summary: Update services on stackato
Home-page: UNKNOWN
Author: Andy McKay
Author-email: andym@mozilla.com
License: MPL 2.0
Platform: UNKNOWN
